{
  "name": "Meraas Design System (Extracted)",
  "source": "https://meraas.framer.website/",
  "colors": {
    "background": {
      "base": "#edeae1",
      "alt": "#e5e2d9",
      "dark": "#141714"
    },
    "text": {
      "primary": "#000000",
      "secondary": "#2b2b2b",
      "muted": "#575656",
      "light": "#b3b0a6"
    },
    "accent": {
      "green": "#3f4d3d",
      "green_light": "#4e6b4e",
      "gold": "#ab6b18"
    }
  },
  "typography": {
    "font_families": {
      "sans": "DM Sans",
      "serif": "Spectral",
      "mono": "Fragment Mono",
      "ui": "Geist"
    },
    "weights": [300, 400, 700, 800, 900]
  }
}
